pysmbserver/__init__.py
pysmbserver/cli.py
pysmbserver/crypto.py
pysmbserver/dcerpc/__init__.py
pysmbserver/dcerpc/v5/__init__.py
pysmbserver/dcerpc/v5/dtypes.py
pysmbserver/dcerpc/v5/enum.py
pysmbserver/dcerpc/v5/ndr.py
pysmbserver/dcerpc/v5/rpcrt.py
pysmbserver/dcerpc/v5/srvs.py
pysmbserver/dcerpc/v5/wkst.py
pysmbserver/hresult_errors.py
pysmbserver/identity_log.py
pysmbserver/krb5/__init__.py
pysmbserver/krb5/asn1.py
pysmbserver/krb5/ccache.py
pysmbserver/krb5/constants.py
pysmbserver/krb5/crypto.py
pysmbserver/krb5/gssapi.py
pysmbserver/krb5/kerberosv5.py
pysmbserver/krb5/types.py
pysmbserver/logger.py
pysmbserver/nmb.py
pysmbserver/nt_errors.py
pysmbserver/ntlm.py
pysmbserver/smb.py
pysmbserver/smb3.py
pysmbserver/smb3structs.py
pysmbserver/smbconnection.py
pysmbserver/smbserver.py
pysmbserver/spnego.py
pysmbserver/structure.py
pysmbserver/system_errors.py
pysmbserver/uuid.py
pysmbserver-0.1.1.dist-info/entry_points.txt
pysmbserver-0.1.1.dist-info/licenses/LICENSE
pysmbserver-0.1.1.dist-info/METADATA
pysmbserver-0.1.1.dist-info/WHEEL
pysmbserver-0.1.1.dist-info/RECORD
