Metadata-Version: 2.4
Name: pysmbserver
Version: 0.1.1
Summary: A simple, lightweight, and customizable SMB (Server Message Block) server implementation in Python.
License-File: LICENSE
Author: CobblePot59
Author-email: 38343920+CobblePot59@users.noreply.github.com
Requires-Python: >=3.13
Classifier: Programming Language :: Python :: 3
Classifier: Programming Language :: Python :: 3.13
Classifier: Programming Language :: Python :: 3.14
Requires-Dist: pyasn1 (>=0.6.1,<0.7.0)
Requires-Dist: pycryptodomex (>=3.23.0,<4.0.0)
Requires-Dist: six (>=1.17.0,<2.0.0)
Project-URL: Homepage, https://github.com/CobblePot59/pysmbserver
Project-URL: Issues, https://github.com/CobblePot59/pysmbserver/issues
Project-URL: Repository, https://github.com/CobblePot59/pysmbserver
